{
    "evaluciones": [{
            "examen_ID": 1,
            "nombre_examen": "Examen 1",
            "status": "I",
            "aciertos": 9,
            "num_preguntas_Contestadas": 10,
            "total_Preguntas": 20,
            "intentos": 0
        },
        {
            "examen_ID": 2,
            "nombre_examen": "Examen 2",
            "status": "T",
            "aciertos": 9,
            "num_preguntas_Contestadas": 10,
            "total_Preguntas": 20,
            "intentos": 0
        },
        {
            "examen_ID": 3,
            "nombre_examen": "Examen 2",
            "status": "N",
            "aciertos": 9,
            "num_preguntas_Contestadas": 10,
            "total_Preguntas": 20,
            "intentos": 0
        }
    ]
}